locust_jtl_logger.py
locust_jtl_logger-0.0.2.dist-info/LICENSE
locust_jtl_logger-0.0.2.dist-info/METADATA
locust_jtl_logger-0.0.2.dist-info/WHEEL
locust_jtl_logger-0.0.2.dist-info/top_level.txt
locust_jtl_logger-0.0.2.dist-info/RECORD
